src/__init__.py
src/hello.py
test_repo_v2-0.0.12.dist-info/METADATA
test_repo_v2-0.0.12.dist-info/WHEEL
test_repo_v2-0.0.12.dist-info/RECORD
